[{
  "name": "客户",
  "key": "Account",
  "file": "ACCOUNT-1.0.json",
  "source": "https://getrebuild.com/",
  "author": "REBUILD",
  "updated": "2019-04-29"
}, {
  "name": "产品",
  "key": "Product",
  "file": "PRODUCT-1.0.json",
  "source": "https://getrebuild.com/",
  "author": "REBUILD",
  "updated": "2020-04-02"
}, {
  "name": "订单",
  "key": "SalesOrder",
  "file": "SALESORDER-1.0.json",
  "source": "https://getrebuild.com/",
  "author": "REBUILD",
  "updated": "2020-04-02",
  "refs": [ "Account", "Product" ]
}]
